{
  "film" : {
    "title" : "The Phantom Menace",
    "director" : "George Lucas",
    "producer" : "Rick McCallum",
    "url" : "https://swapi.info/api/films/4",
    "characters" : [ "https://swapi.info/api/people/2", "https://swapi.info/api/people/3", "https://swapi.info/api/people/10", "https://swapi.info/api/people/11", "https://swapi.info/api/people/16", "https://swapi.info/api/people/20", "https://swapi.info/api/people/21", "https://swapi.info/api/people/32", "https://swapi.info/api/people/33", "https://swapi.info/api/people/34", "https://swapi.info/api/people/35", "https://swapi.info/api/people/36", "https://swapi.info/api/people/37", "https://swapi.info/api/people/38", "https://swapi.info/api/people/39", "https://swapi.info/api/people/40", "https://swapi.info/api/people/41", "https://swapi.info/api/people/42", "https://swapi.info/api/people/43", "https://swapi.info/api/people/44", "https://swapi.info/api/people/46", "https://swapi.info/api/people/47", "https://swapi.info/api/people/48", "https://swapi.info/api/people/49", "https://swapi.info/api/people/50", "https://swapi.info/api/people/51", "https://swapi.info/api/people/52", "https://swapi.info/api/people/53", "https://swapi.info/api/people/54", "https://swapi.info/api/people/55", "https://swapi.info/api/people/56", "https://swapi.info/api/people/57", "https://swapi.info/api/people/58", "https://swapi.info/api/people/59" ],
    "planets" : [ "https://swapi.info/api/planets/1", "https://swapi.info/api/planets/8", "https://swapi.info/api/planets/9" ],
    "species" : [ "https://swapi.info/api/species/1", "https://swapi.info/api/species/2", "https://swapi.info/api/species/6", "https://swapi.info/api/species/11", "https://swapi.info/api/species/12", "https://swapi.info/api/species/13", "https://swapi.info/api/species/14", "https://swapi.info/api/species/15", "https://swapi.info/api/species/16", "https://swapi.info/api/species/17", "https://swapi.info/api/species/18", "https://swapi.info/api/species/19", "https://swapi.info/api/species/20", "https://swapi.info/api/species/21", "https://swapi.info/api/species/22", "https://swapi.info/api/species/23", "https://swapi.info/api/species/24", "https://swapi.info/api/species/25", "https://swapi.info/api/species/26", "https://swapi.info/api/species/27" ],
    "starships" : [ "https://swapi.info/api/starships/31", "https://swapi.info/api/starships/32", "https://swapi.info/api/starships/39", "https://swapi.info/api/starships/40", "https://swapi.info/api/starships/41" ],
    "vehicles" : [ "https://swapi.info/api/vehicles/33", "https://swapi.info/api/vehicles/34", "https://swapi.info/api/vehicles/35", "https://swapi.info/api/vehicles/36", "https://swapi.info/api/vehicles/37", "https://swapi.info/api/vehicles/38", "https://swapi.info/api/vehicles/42" ],
    "episode_id" : 1,
    "opening_crawl" : "Turmoil has engulfed the\r\nGalactic Republic. The taxation\r\nof trade routes to outlying star\r\nsystems is in dispute.\r\n\r\nHoping to resolve the matter\r\nwith a blockade of deadly\r\nbattleships, the greedy Trade\r\nFederation has stopped all\r\nshipping to the small planet\r\nof Naboo.\r\n\r\nWhile the Congress of the\r\nRepublic endlessly debates\r\nthis alarming chain of events,\r\nthe Supreme Chancellor has\r\nsecretly dispatched two Jedi\r\nKnights, the guardians of\r\npeace and justice in the\r\ngalaxy, to settle the conflict....",
    "release_date" : "1999-05-19"
  },
  "planets" : [ {
    "name" : "Tatooine",
    "climate" : "arid",
    "terrain" : "desert",
    "diameter" : "10465",
    "population" : "200000",
    "url" : "https://swapi.info/api/planets/1",
    "rotation_period" : "23",
    "orbital_period" : "304"
  }, {
    "name" : "Naboo",
    "climate" : "temperate",
    "terrain" : "grassy hills, swamps, forests, mountains",
    "diameter" : "12120",
    "population" : "4500000000",
    "url" : "https://swapi.info/api/planets/8",
    "rotation_period" : "26",
    "orbital_period" : "312"
  }, {
    "name" : "Coruscant",
    "climate" : "temperate",
    "terrain" : "cityscape, mountains",
    "diameter" : "12240",
    "population" : "1000000000000",
    "url" : "https://swapi.info/api/planets/9",
    "rotation_period" : "24",
    "orbital_period" : "368"
  } ],
  "species" : [ {
    "name" : "Human",
    "classification" : "mammal",
    "designation" : "sentient",
    "language" : "Galactic Basic",
    "url" : "https://swapi.info/api/species/1",
    "average_height" : "180",
    "skin_colors" : "caucasian, black, asian, hispanic",
    "eye_colors" : "brown, blue, green, hazel, grey, amber",
    "average_lifespan" : "120",
    "hair_colors" : "blonde, brown, black, red"
  }, {
    "name" : "Droid",
    "classification" : "artificial",
    "designation" : "sentient",
    "language" : "n/a",
    "url" : "https://swapi.info/api/species/2",
    "average_height" : "n/a",
    "skin_colors" : "n/a",
    "eye_colors" : "n/a",
    "average_lifespan" : "indefinite",
    "hair_colors" : "n/a"
  }, {
    "name" : "Yoda's species",
    "classification" : "mammal",
    "designation" : "sentient",
    "language" : "Galactic basic",
    "url" : "https://swapi.info/api/species/6",
    "average_height" : "66",
    "skin_colors" : "green, yellow",
    "eye_colors" : "brown, green, yellow",
    "average_lifespan" : "900",
    "hair_colors" : "brown, white"
  }, {
    "name" : "Neimodian",
    "classification" : "unknown",
    "designation" : "sentient",
    "language" : "Neimoidia",
    "url" : "https://swapi.info/api/species/11",
    "average_height" : "180",
    "skin_colors" : "grey, green",
    "eye_colors" : "red, pink",
    "average_lifespan" : "unknown",
    "hair_colors" : "none"
  }, {
    "name" : "Gungan",
    "classification" : "amphibian",
    "designation" : "sentient",
    "language" : "Gungan basic",
    "url" : "https://swapi.info/api/species/12",
    "average_height" : "190",
    "skin_colors" : "brown, green",
    "eye_colors" : "orange",
    "average_lifespan" : "unknown",
    "hair_colors" : "none"
  }, {
    "name" : "Toydarian",
    "classification" : "mammal",
    "designation" : "sentient",
    "language" : "Toydarian",
    "url" : "https://swapi.info/api/species/13",
    "average_height" : "120",
    "skin_colors" : "blue, green, grey",
    "eye_colors" : "yellow",
    "average_lifespan" : "91",
    "hair_colors" : "none"
  }, {
    "name" : "Dug",
    "classification" : "mammal",
    "designation" : "sentient",
    "language" : "Dugese",
    "url" : "https://swapi.info/api/species/14",
    "average_height" : "100",
    "skin_colors" : "brown, purple, grey, red",
    "eye_colors" : "yellow, blue",
    "average_lifespan" : "unknown",
    "hair_colors" : "none"
  }, {
    "name" : "Twi'lek",
    "classification" : "mammals",
    "designation" : "sentient",
    "language" : "Twi'leki",
    "url" : "https://swapi.info/api/species/15",
    "average_height" : "200",
    "skin_colors" : "orange, yellow, blue, green, pink, purple, tan",
    "eye_colors" : "blue, brown, orange, pink",
    "average_lifespan" : "unknown",
    "hair_colors" : "none"
  }, {
    "name" : "Aleena",
    "classification" : "reptile",
    "designation" : "sentient",
    "language" : "Aleena",
    "url" : "https://swapi.info/api/species/16",
    "average_height" : "80",
    "skin_colors" : "blue, gray",
    "eye_colors" : "unknown",
    "average_lifespan" : "79",
    "hair_colors" : "none"
  }, {
    "name" : "Vulptereen",
    "classification" : "unknown",
    "designation" : "sentient",
    "language" : "vulpterish",
    "url" : "https://swapi.info/api/species/17",
    "average_height" : "100",
    "skin_colors" : "grey",
    "eye_colors" : "yellow",
    "average_lifespan" : "unknown",
    "hair_colors" : "none"
  }, {
    "name" : "Xexto",
    "classification" : "unknown",
    "designation" : "sentient",
    "language" : "Xextese",
    "url" : "https://swapi.info/api/species/18",
    "average_height" : "125",
    "skin_colors" : "grey, yellow, purple",
    "eye_colors" : "black",
    "average_lifespan" : "unknown",
    "hair_colors" : "none"
  }, {
    "name" : "Toong",
    "classification" : "unknown",
    "designation" : "sentient",
    "language" : "Tundan",
    "url" : "https://swapi.info/api/species/19",
    "average_height" : "200",
    "skin_colors" : "grey, green, yellow",
    "eye_colors" : "orange",
    "average_lifespan" : "unknown",
    "hair_colors" : "none"
  }, {
    "name" : "Cerean",
    "classification" : "mammal",
    "designation" : "sentient",
    "language" : "Cerean",
    "url" : "https://swapi.info/api/species/20",
    "average_height" : "200",
    "skin_colors" : "pale pink",
    "eye_colors" : "hazel",
    "average_lifespan" : "unknown",
    "hair_colors" : "red, blond, black, white"
  }, {
    "name" : "Nautolan",
    "classification" : "amphibian",
    "designation" : "sentient",
    "language" : "Nautila",
    "url" : "https://swapi.info/api/species/21",
    "average_height" : "180",
    "skin_colors" : "green, blue, brown, red",
    "eye_colors" : "black",
    "average_lifespan" : "70",
    "hair_colors" : "none"
  }, {
    "name" : "Zabrak",
    "classification" : "mammal",
    "designation" : "sentient",
    "language" : "Zabraki",
    "url" : "https://swapi.info/api/species/22",
    "average_height" : "180",
    "skin_colors" : "pale, brown, red, orange, yellow",
    "eye_colors" : "brown, orange",
    "average_lifespan" : "unknown",
    "hair_colors" : "black"
  }, {
    "name" : "Tholothian",
    "classification" : "mammal",
    "designation" : "sentient",
    "language" : "unknown",
    "url" : "https://swapi.info/api/species/23",
    "average_height" : "unknown",
    "skin_colors" : "dark",
    "eye_colors" : "blue, indigo",
    "average_lifespan" : "unknown",
    "hair_colors" : "unknown"
  }, {
    "name" : "Iktotchi",
    "classification" : "unknown",
    "designation" : "sentient",
    "language" : "Iktotchese",
    "url" : "https://swapi.info/api/species/24",
    "average_height" : "180",
    "skin_colors" : "pink",
    "eye_colors" : "orange",
    "average_lifespan" : "unknown",
    "hair_colors" : "none"
  }, {
    "name" : "Quermian",
    "classification" : "mammal",
    "designation" : "sentient",
    "language" : "Quermian",
    "url" : "https://swapi.info/api/species/25",
    "average_height" : "240",
    "skin_colors" : "white",
    "eye_colors" : "yellow",
    "average_lifespan" : "86",
    "hair_colors" : "none"
  }, {
    "name" : "Kel Dor",
    "classification" : "unknown",
    "designation" : "sentient",
    "language" : "Kel Dor",
    "url" : "https://swapi.info/api/species/26",
    "average_height" : "180",
    "skin_colors" : "peach, orange, red",
    "eye_colors" : "black, silver",
    "average_lifespan" : "70",
    "hair_colors" : "none"
  }, {
    "name" : "Chagrian",
    "classification" : "amphibian",
    "designation" : "sentient",
    "language" : "Chagria",
    "url" : "https://swapi.info/api/species/27",
    "average_height" : "190",
    "skin_colors" : "blue",
    "eye_colors" : "blue",
    "average_lifespan" : "unknown",
    "hair_colors" : "none"
  } ],
  "people" : [ {
    "name" : "C-3PO",
    "height" : "167",
    "mass" : "75",
    "gender" : "n/a",
    "url" : "https://swapi.info/api/people/2",
    "starships" : [ ],
    "vehicles" : [ ],
    "hair_color" : "n/a",
    "skin_color" : "gold",
    "eye_color" : "yellow",
    "birth_year" : "112BBY"
  }, {
    "name" : "R2-D2",
    "height" : "96",
    "mass" : "32",
    "gender" : "n/a",
    "url" : "https://swapi.info/api/people/3",
    "starships" : [ ],
    "vehicles" : [ ],
    "hair_color" : "n/a",
    "skin_color" : "white, blue",
    "eye_color" : "red",
    "birth_year" : "33BBY"
  }, {
    "name" : "Obi-Wan Kenobi",
    "height" : "182",
    "mass" : "77",
    "gender" : "male",
    "url" : "https://swapi.info/api/people/10",
    "starships" : [ "https://swapi.info/api/starships/48", "https://swapi.info/api/starships/59", "https://swapi.info/api/starships/64", "https://swapi.info/api/starships/65", "https://swapi.info/api/starships/74" ],
    "vehicles" : [ "https://swapi.info/api/vehicles/38" ],
    "hair_color" : "auburn, white",
    "skin_color" : "fair",
    "eye_color" : "blue-gray",
    "birth_year" : "57BBY"
  }, {
    "name" : "Anakin Skywalker",
    "height" : "188",
    "mass" : "84",
    "gender" : "male",
    "url" : "https://swapi.info/api/people/11",
    "starships" : [ "https://swapi.info/api/starships/39", "https://swapi.info/api/starships/59", "https://swapi.info/api/starships/65" ],
    "vehicles" : [ "https://swapi.info/api/vehicles/44", "https://swapi.info/api/vehicles/46" ],
    "hair_color" : "blond",
    "skin_color" : "fair",
    "eye_color" : "blue",
    "birth_year" : "41.9BBY"
  }, {
    "name" : "Jabba Desilijic Tiure",
    "height" : "175",
    "mass" : "1,358",
    "gender" : "hermaphrodite",
    "url" : "https://swapi.info/api/people/16",
    "starships" : [ ],
    "vehicles" : [ ],
    "hair_color" : "n/a",
    "skin_color" : "green-tan, brown",
    "eye_color" : "orange",
    "birth_year" : "600BBY"
  }, {
    "name" : "Yoda",
    "height" : "66",
    "mass" : "17",
    "gender" : "male",
    "url" : "https://swapi.info/api/people/20",
    "starships" : [ ],
    "vehicles" : [ ],
    "hair_color" : "white",
    "skin_color" : "green",
    "eye_color" : "brown",
    "birth_year" : "896BBY"
  }, {
    "name" : "Palpatine",
    "height" : "170",
    "mass" : "75",
    "gender" : "male",
    "url" : "https://swapi.info/api/people/21",
    "starships" : [ ],
    "vehicles" : [ ],
    "hair_color" : "grey",
    "skin_color" : "pale",
    "eye_color" : "yellow",
    "birth_year" : "82BBY"
  }, {
    "name" : "Qui-Gon Jinn",
    "height" : "193",
    "mass" : "89",
    "gender" : "male",
    "url" : "https://swapi.info/api/people/32",
    "starships" : [ ],
    "vehicles" : [ "https://swapi.info/api/vehicles/38" ],
    "hair_color" : "brown",
    "skin_color" : "fair",
    "eye_color" : "blue",
    "birth_year" : "92BBY"
  }, {
    "name" : "Nute Gunray",
    "height" : "191",
    "mass" : "90",
    "gender" : "male",
    "url" : "https://swapi.info/api/people/33",
    "starships" : [ ],
    "vehicles" : [ ],
    "hair_color" : "none",
    "skin_color" : "mottled green",
    "eye_color" : "red",
    "birth_year" : "unknown"
  }, {
    "name" : "Finis Valorum",
    "height" : "170",
    "mass" : "unknown",
    "gender" : "male",
    "url" : "https://swapi.info/api/people/34",
    "starships" : [ ],
    "vehicles" : [ ],
    "hair_color" : "blond",
    "skin_color" : "fair",
    "eye_color" : "blue",
    "birth_year" : "91BBY"
  }, {
    "name" : "Padmé Amidala",
    "height" : "185",
    "mass" : "45",
    "gender" : "female",
    "url" : "https://swapi.info/api/people/35",
    "starships" : [ "https://swapi.info/api/starships/39", "https://swapi.info/api/starships/49", "https://swapi.info/api/starships/64" ],
    "vehicles" : [ ],
    "hair_color" : "brown",
    "skin_color" : "light",
    "eye_color" : "brown",
    "birth_year" : "46BBY"
  }, {
    "name" : "Jar Jar Binks",
    "height" : "196",
    "mass" : "66",
    "gender" : "male",
    "url" : "https://swapi.info/api/people/36",
    "starships" : [ ],
    "vehicles" : [ ],
    "hair_color" : "none",
    "skin_color" : "orange",
    "eye_color" : "orange",
    "birth_year" : "52BBY"
  }, {
    "name" : "Roos Tarpals",
    "height" : "224",
    "mass" : "82",
    "gender" : "male",
    "url" : "https://swapi.info/api/people/37",
    "starships" : [ ],
    "vehicles" : [ ],
    "hair_color" : "none",
    "skin_color" : "grey",
    "eye_color" : "orange",
    "birth_year" : "unknown"
  }, {
    "name" : "Rugor Nass",
    "height" : "206",
    "mass" : "unknown",
    "gender" : "male",
    "url" : "https://swapi.info/api/people/38",
    "starships" : [ ],
    "vehicles" : [ ],
    "hair_color" : "none",
    "skin_color" : "green",
    "eye_color" : "orange",
    "birth_year" : "unknown"
  }, {
    "name" : "Ric Olié",
    "height" : "183",
    "mass" : "unknown",
    "gender" : "male",
    "url" : "https://swapi.info/api/people/39",
    "starships" : [ "https://swapi.info/api/starships/40" ],
    "vehicles" : [ ],
    "hair_color" : "brown",
    "skin_color" : "fair",
    "eye_color" : "blue",
    "birth_year" : "unknown"
  }, {
    "name" : "Watto",
    "height" : "137",
    "mass" : "unknown",
    "gender" : "male",
    "url" : "https://swapi.info/api/people/40",
    "starships" : [ ],
    "vehicles" : [ ],
    "hair_color" : "black",
    "skin_color" : "blue, grey",
    "eye_color" : "yellow",
    "birth_year" : "unknown"
  }, {
    "name" : "Sebulba",
    "height" : "112",
    "mass" : "40",
    "gender" : "male",
    "url" : "https://swapi.info/api/people/41",
    "starships" : [ ],
    "vehicles" : [ ],
    "hair_color" : "none",
    "skin_color" : "grey, red",
    "eye_color" : "orange",
    "birth_year" : "unknown"
  }, {
    "name" : "Quarsh Panaka",
    "height" : "183",
    "mass" : "unknown",
    "gender" : "male",
    "url" : "https://swapi.info/api/people/42",
    "starships" : [ ],
    "vehicles" : [ ],
    "hair_color" : "black",
    "skin_color" : "dark",
    "eye_color" : "brown",
    "birth_year" : "62BBY"
  }, {
    "name" : "Shmi Skywalker",
    "height" : "163",
    "mass" : "unknown",
    "gender" : "female",
    "url" : "https://swapi.info/api/people/43",
    "starships" : [ ],
    "vehicles" : [ ],
    "hair_color" : "black",
    "skin_color" : "fair",
    "eye_color" : "brown",
    "birth_year" : "72BBY"
  }, {
    "name" : "Darth Maul",
    "height" : "175",
    "mass" : "80",
    "gender" : "male",
    "url" : "https://swapi.info/api/people/44",
    "starships" : [ "https://swapi.info/api/starships/41" ],
    "vehicles" : [ "https://swapi.info/api/vehicles/42" ],
    "hair_color" : "none",
    "skin_color" : "red",
    "eye_color" : "yellow",
    "birth_year" : "54BBY"
  }, {
    "name" : "Ayla Secura",
    "height" : "178",
    "mass" : "55",
    "gender" : "female",
    "url" : "https://swapi.info/api/people/46",
    "starships" : [ ],
    "vehicles" : [ ],
    "hair_color" : "none",
    "skin_color" : "blue",
    "eye_color" : "hazel",
    "birth_year" : "48BBY"
  }, {
    "name" : "Ratts Tyerel",
    "height" : "79",
    "mass" : "15",
    "gender" : "male",
    "url" : "https://swapi.info/api/people/47",
    "starships" : [ ],
    "vehicles" : [ ],
    "hair_color" : "none",
    "skin_color" : "grey, blue",
    "eye_color" : "unknown",
    "birth_year" : "unknown"
  }, {
    "name" : "Dud Bolt",
    "height" : "94",
    "mass" : "45",
    "gender" : "male",
    "url" : "https://swapi.info/api/people/48",
    "starships" : [ ],
    "vehicles" : [ ],
    "hair_color" : "none",
    "skin_color" : "blue, grey",
    "eye_color" : "yellow",
    "birth_year" : "unknown"
  }, {
    "name" : "Gasgano",
    "height" : "122",
    "mass" : "unknown",
    "gender" : "male",
    "url" : "https://swapi.info/api/people/49",
    "starships" : [ ],
    "vehicles" : [ ],
    "hair_color" : "none",
    "skin_color" : "white, blue",
    "eye_color" : "black",
    "birth_year" : "unknown"
  }, {
    "name" : "Ben Quadinaros",
    "height" : "163",
    "mass" : "65",
    "gender" : "male",
    "url" : "https://swapi.info/api/people/50",
    "starships" : [ ],
    "vehicles" : [ ],
    "hair_color" : "none",
    "skin_color" : "grey, green, yellow",
    "eye_color" : "orange",
    "birth_year" : "unknown"
  }, {
    "name" : "Mace Windu",
    "height" : "188",
    "mass" : "84",
    "gender" : "male",
    "url" : "https://swapi.info/api/people/51",
    "starships" : [ ],
    "vehicles" : [ ],
    "hair_color" : "none",
    "skin_color" : "dark",
    "eye_color" : "brown",
    "birth_year" : "72BBY"
  }, {
    "name" : "Ki-Adi-Mundi",
    "height" : "198",
    "mass" : "82",
    "gender" : "male",
    "url" : "https://swapi.info/api/people/52",
    "starships" : [ ],
    "vehicles" : [ ],
    "hair_color" : "white",
    "skin_color" : "pale",
    "eye_color" : "yellow",
    "birth_year" : "92BBY"
  }, {
    "name" : "Kit Fisto",
    "height" : "196",
    "mass" : "87",
    "gender" : "male",
    "url" : "https://swapi.info/api/people/53",
    "starships" : [ ],
    "vehicles" : [ ],
    "hair_color" : "none",
    "skin_color" : "green",
    "eye_color" : "black",
    "birth_year" : "unknown"
  }, {
    "name" : "Eeth Koth",
    "height" : "171",
    "mass" : "unknown",
    "gender" : "male",
    "url" : "https://swapi.info/api/people/54",
    "starships" : [ ],
    "vehicles" : [ ],
    "hair_color" : "black",
    "skin_color" : "brown",
    "eye_color" : "brown",
    "birth_year" : "unknown"
  }, {
    "name" : "Adi Gallia",
    "height" : "184",
    "mass" : "50",
    "gender" : "female",
    "url" : "https://swapi.info/api/people/55",
    "starships" : [ ],
    "vehicles" : [ ],
    "hair_color" : "none",
    "skin_color" : "dark",
    "eye_color" : "blue",
    "birth_year" : "unknown"
  }, {
    "name" : "Saesee Tiin",
    "height" : "188",
    "mass" : "unknown",
    "gender" : "male",
    "url" : "https://swapi.info/api/people/56",
    "starships" : [ ],
    "vehicles" : [ ],
    "hair_color" : "none",
    "skin_color" : "pale",
    "eye_color" : "orange",
    "birth_year" : "unknown"
  }, {
    "name" : "Yarael Poof",
    "height" : "264",
    "mass" : "unknown",
    "gender" : "male",
    "url" : "https://swapi.info/api/people/57",
    "starships" : [ ],
    "vehicles" : [ ],
    "hair_color" : "none",
    "skin_color" : "white",
    "eye_color" : "yellow",
    "birth_year" : "unknown"
  }, {
    "name" : "Plo Koon",
    "height" : "188",
    "mass" : "80",
    "gender" : "male",
    "url" : "https://swapi.info/api/people/58",
    "starships" : [ "https://swapi.info/api/starships/48" ],
    "vehicles" : [ ],
    "hair_color" : "none",
    "skin_color" : "orange",
    "eye_color" : "black",
    "birth_year" : "22BBY"
  }, {
    "name" : "Mas Amedda",
    "height" : "196",
    "mass" : "unknown",
    "gender" : "male",
    "url" : "https://swapi.info/api/people/59",
    "starships" : [ ],
    "vehicles" : [ ],
    "hair_color" : "none",
    "skin_color" : "blue",
    "eye_color" : "blue",
    "birth_year" : "unknown"
  } ],
  "starships" : [ {
    "name" : "Scimitar",
    "model" : "Star Courier",
    "manufacturer" : "Republic Sienar Systems",
    "length" : "26.5",
    "crew" : "1",
    "passengers" : "6",
    "url" : "https://swapi.info/api/starships/41",
    "cost_in_credits" : "55000000",
    "max_atmosphering_speed" : "1180",
    "starship_class" : "Space Transport",
    "hyperdrive_rating" : "1.5"
  }, {
    "name" : "Belbullab-22 starfighter",
    "model" : "Belbullab-22 starfighter",
    "manufacturer" : "Feethan Ottraw Scalable Assemblies",
    "length" : "6.71",
    "crew" : "1",
    "passengers" : "0",
    "url" : "https://swapi.info/api/starships/74",
    "cost_in_credits" : "168000",
    "max_atmosphering_speed" : "1100",
    "starship_class" : "starfighter",
    "hyperdrive_rating" : "6"
  }, {
    "name" : "Republic Cruiser",
    "model" : "Consular-class cruiser",
    "manufacturer" : "Corellian Engineering Corporation",
    "length" : "115",
    "crew" : "9",
    "passengers" : "16",
    "url" : "https://swapi.info/api/starships/31",
    "cost_in_credits" : "unknown",
    "max_atmosphering_speed" : "900",
    "starship_class" : "Space cruiser",
    "hyperdrive_rating" : "2.0"
  }, {
    "name" : "Naboo star skiff",
    "model" : "J-type star skiff",
    "manufacturer" : "Theed Palace Space Vessel Engineering Corps/Nubia Star Drives, Incorporated",
    "length" : "29.2",
    "crew" : "3",
    "passengers" : "3",
    "url" : "https://swapi.info/api/starships/64",
    "cost_in_credits" : "unknown",
    "max_atmosphering_speed" : "1050",
    "starship_class" : "yacht",
    "hyperdrive_rating" : "0.5"
  }, {
    "name" : "Naboo Royal Starship",
    "model" : "J-type 327 Nubian royal starship",
    "manufacturer" : "Theed Palace Space Vessel Engineering Corps, Nubia Star Drives",
    "length" : "76",
    "crew" : "8",
    "passengers" : "unknown",
    "url" : "https://swapi.info/api/starships/40",
    "cost_in_credits" : "unknown",
    "max_atmosphering_speed" : "920",
    "starship_class" : "yacht",
    "hyperdrive_rating" : "1.8"
  }, {
    "name" : "Droid control ship",
    "model" : "Lucrehulk-class Droid Control Ship",
    "manufacturer" : "Hoersch-Kessel Drive, Inc.",
    "length" : "3170",
    "crew" : "175",
    "passengers" : "139000",
    "url" : "https://swapi.info/api/starships/32",
    "cost_in_credits" : "unknown",
    "max_atmosphering_speed" : "n/a",
    "starship_class" : "Droid control ship",
    "hyperdrive_rating" : "2.0"
  }, {
    "name" : "Jedi Interceptor",
    "model" : "Eta-2 Actis-class light interceptor",
    "manufacturer" : "Kuat Systems Engineering",
    "length" : "5.47",
    "crew" : "1",
    "passengers" : "0",
    "url" : "https://swapi.info/api/starships/65",
    "cost_in_credits" : "320000",
    "max_atmosphering_speed" : "1500",
    "starship_class" : "starfighter",
    "hyperdrive_rating" : "1.0"
  }, {
    "name" : "H-type Nubian yacht",
    "model" : "H-type Nubian yacht",
    "manufacturer" : "Theed Palace Space Vessel Engineering Corps",
    "length" : "47.9",
    "crew" : "4",
    "passengers" : "unknown",
    "url" : "https://swapi.info/api/starships/49",
    "cost_in_credits" : "unknown",
    "max_atmosphering_speed" : "8000",
    "starship_class" : "yacht",
    "hyperdrive_rating" : "0.9"
  }, {
    "name" : "Naboo fighter",
    "model" : "N-1 starfighter",
    "manufacturer" : "Theed Palace Space Vessel Engineering Corps",
    "length" : "11",
    "crew" : "1",
    "passengers" : "0",
    "url" : "https://swapi.info/api/starships/39",
    "cost_in_credits" : "200000",
    "max_atmosphering_speed" : "1100",
    "starship_class" : "Starfighter",
    "hyperdrive_rating" : "1.0"
  }, {
    "name" : "Jedi starfighter",
    "model" : "Delta-7 Aethersprite-class interceptor",
    "manufacturer" : "Kuat Systems Engineering",
    "length" : "8",
    "crew" : "1",
    "passengers" : "0",
    "url" : "https://swapi.info/api/starships/48",
    "cost_in_credits" : "180000",
    "max_atmosphering_speed" : "1150",
    "starship_class" : "Starfighter",
    "hyperdrive_rating" : "1.0"
  }, {
    "name" : "Trade Federation cruiser",
    "model" : "Providence-class carrier/destroyer",
    "manufacturer" : "Rendili StarDrive, Free Dac Volunteers Engineering corps.",
    "length" : "1088",
    "crew" : "600",
    "passengers" : "48247",
    "url" : "https://swapi.info/api/starships/59",
    "cost_in_credits" : "125000000",
    "max_atmosphering_speed" : "1050",
    "starship_class" : "capital ship",
    "hyperdrive_rating" : "1.5"
  } ],
  "vehicles" : [ {
    "name" : "Sith speeder",
    "model" : "FC-20 speeder bike",
    "manufacturer" : "Razalon",
    "length" : "1.5",
    "crew" : "1",
    "passengers" : "0",
    "url" : "https://swapi.info/api/vehicles/42",
    "cost_in_credits" : "4000",
    "vehicle_class" : "speeder"
  }, {
    "name" : "Vulture Droid",
    "model" : "Vulture-class droid starfighter",
    "manufacturer" : "Haor Chall Engineering, Baktoid Armor Workshop",
    "length" : "3.5",
    "crew" : "0",
    "passengers" : "0",
    "url" : "https://swapi.info/api/vehicles/33",
    "cost_in_credits" : "unknown",
    "vehicle_class" : "starfighter"
  }, {
    "name" : "Zephyr-G swoop bike",
    "model" : "Zephyr-G swoop bike",
    "manufacturer" : "Mobquet Swoops and Speeders",
    "length" : "3.68",
    "crew" : "1",
    "passengers" : "1",
    "url" : "https://swapi.info/api/vehicles/44",
    "cost_in_credits" : "5750",
    "vehicle_class" : "repulsorcraft"
  }, {
    "name" : "Multi-Troop Transport",
    "model" : "Multi-Troop Transport",
    "manufacturer" : "Baktoid Armor Workshop",
    "length" : "31",
    "crew" : "4",
    "passengers" : "112",
    "url" : "https://swapi.info/api/vehicles/34",
    "cost_in_credits" : "138000",
    "vehicle_class" : "repulsorcraft"
  }, {
    "name" : "Armored Assault Tank",
    "model" : "Armoured Assault Tank",
    "manufacturer" : "Baktoid Armor Workshop",
    "length" : "9.75",
    "crew" : "4",
    "passengers" : "6",
    "url" : "https://swapi.info/api/vehicles/35",
    "cost_in_credits" : "unknown",
    "vehicle_class" : "repulsorcraft"
  }, {
    "name" : "XJ-6 airspeeder",
    "model" : "XJ-6 airspeeder",
    "manufacturer" : "Narglatch AirTech prefabricated kit",
    "length" : "6.23",
    "crew" : "1",
    "passengers" : "1",
    "url" : "https://swapi.info/api/vehicles/46",
    "cost_in_credits" : "unknown",
    "vehicle_class" : "airspeeder"
  }, {
    "name" : "Single Trooper Aerial Platform",
    "model" : "Single Trooper Aerial Platform",
    "manufacturer" : "Baktoid Armor Workshop",
    "length" : "2",
    "crew" : "1",
    "passengers" : "0",
    "url" : "https://swapi.info/api/vehicles/36",
    "cost_in_credits" : "2500",
    "vehicle_class" : "repulsorcraft"
  }, {
    "name" : "C-9979 landing craft",
    "model" : "C-9979 landing craft",
    "manufacturer" : "Haor Chall Engineering",
    "length" : "210",
    "crew" : "140",
    "passengers" : "284",
    "url" : "https://swapi.info/api/vehicles/37",
    "cost_in_credits" : "200000",
    "vehicle_class" : "landing craft"
  }, {
    "name" : "Tribubble bongo",
    "model" : "Tribubble bongo",
    "manufacturer" : "Otoh Gunga Bongameken Cooperative",
    "length" : "15",
    "crew" : "1",
    "passengers" : "2",
    "url" : "https://swapi.info/api/vehicles/38",
    "cost_in_credits" : "unknown",
    "vehicle_class" : "submarine"
  } ]
}